palatable/__init__.py
palatable/color.py
palatable/course.py
palatable/graph.py
palatable/graphbuilder.py
palatable/graphpainter.py
palatable/helpers.py
palatable/scheduler.py
palatable/student.py
palatable-0.1.2.dist-info/LICENSE
palatable-0.1.2.dist-info/METADATA
palatable-0.1.2.dist-info/WHEEL
palatable-0.1.2.dist-info/entry_points.txt
palatable-0.1.2.dist-info/top_level.txt
palatable-0.1.2.dist-info/RECORD
