Metadata-Version: 2.1
Name: palatable
Version: 0.1.2
Summary: Fast, reliable exams scheduler
Home-page: https://github.com/iamjazzar/palatable
Author: Ahmed Jazzar
Author-email: me@ahmedjazzar.com
License: GNU Affero General Public License v3
Classifier: Development Status :: 5 - Production/Stable
Classifier: Intended Audience :: Developers
Classifier: Operating System :: OS Independent
Classifier: Programming Language :: Python :: 3
Classifier: Programming Language :: Python :: 3.7
Classifier: Programming Language :: Python :: 3.8
Classifier: Programming Language :: Python :: 3.9
Classifier: Programming Language :: Python :: 3.10
Classifier: License :: OSI Approved :: GNU Affero General Public License v3
Classifier: Topic :: Software Development
License-File: LICENSE
Requires-Dist: Faker (==13.11.1)
Requires-Dist: tabulate (==0.8.9)
